dockgen/__init__.py
dockgen/__main__.py
dockgen/conf.py
dockgen/forge.py
dockgen/project.py
dockgen/py.typed
dockgen/templates/layer.Dockerfile
dockgen/templates/main.Dockerfile
dockgen-0.5.0.dist-info/WHEEL
dockgen-0.5.0.dist-info/entry_points.txt
dockgen-0.5.0.dist-info/METADATA
dockgen-0.5.0.dist-info/RECORD
