Metadata-Version: 2.4
Name: dockgen
Version: 0.5.0
Summary: Generate fresh docker images
Author: Guilhem Saurel
Author-email: Guilhem Saurel <guilhem.saurel@laas.fr>
License-Expression: BSD-2-Clause
Requires-Dist: httpx>=0.28.1
Requires-Dist: jinja2>=3.1.6
Requires-Python: >=3.13
